LICENSE.md
MANIFEST.in
README.dst
README.md
setup.py
cfg/__init__.py
cfg/baseline/r50-csp.yaml
cfg/baseline/x50-csp.yaml
cfg/baseline/yolor-csp-x.yaml
cfg/baseline/yolor-csp.yaml
cfg/baseline/yolor-d6.yaml
cfg/baseline/yolor-e6.yaml
cfg/baseline/yolor-p6.yaml
cfg/baseline/yolor-w6.yaml
cfg/baseline/yolov3-spp.yaml
cfg/baseline/yolov3.yaml
cfg/baseline/yolov4-csp.yaml
cfg/deploy/yolov7-d6.yaml
cfg/deploy/yolov7-e6.yaml
cfg/deploy/yolov7-e6e.yaml
cfg/deploy/yolov7-tiny-silu.yaml
cfg/deploy/yolov7-tiny.yaml
cfg/deploy/yolov7-w6.yaml
cfg/deploy/yolov7.yaml
cfg/deploy/yolov7x.yaml
cfg/training/yolov7-d6.yaml
cfg/training/yolov7-e6.yaml
cfg/training/yolov7-e6e.yaml
cfg/training/yolov7-tiny.yaml
cfg/training/yolov7-w6.yaml
cfg/training/yolov7.yaml
cfg/training/yolov7x.yaml
data/__init__.py
data/coco.yaml
data/hyp.scratch.custom.yaml
data/hyp.scratch.p5.yaml
data/hyp.scratch.p6.yaml
data/hyp.scratch.tiny.yaml
inference/__init__.py
inference/images/bus.jpg
inference/images/horses.jpg
inference/images/image1.jpg
inference/images/image2.jpg
inference/images/image3.jpg
inference/images/zidane.jpg
models/__init__.py
models/common.py
models/experimental.py
models/yolo.py
python_scripts/__init__.py
python_scripts/detect.py
python_scripts/export.py
python_scripts/hubconf.py
python_scripts/test.py
python_scripts/train.py
python_scripts/train_aux.py
utils/__init__.py
utils/activations.py
utils/add_nms.py
utils/autoanchor.py
utils/datasets.py
utils/general.py
utils/google_utils.py
utils/loss.py
utils/metrics.py
utils/plots.py
utils/torch_utils.py
utils/aws/__init__.py
utils/aws/resume.py
utils/wandb_logging/__init__.py
utils/wandb_logging/log_dataset.py
utils/wandb_logging/wandb_utils.py
yolov7_wky.egg-info/PKG-INFO
yolov7_wky.egg-info/SOURCES.txt
yolov7_wky.egg-info/dependency_links.txt
yolov7_wky.egg-info/entry_points.txt
yolov7_wky.egg-info/requires.txt
yolov7_wky.egg-info/top_level.txt