Metadata-Version: 2.1
Name: yolov7-wky
Version: 2023.1.9.3
Author: biantsh
Requires-Python: >=3.10
License-File: LICENSE.md
